{
"recognize" : "to identify someone or something from having encountered them before, know again",
"preposition" : "a word such as into, in, or for, that comes before a noun. It describes the relationship between the noun and what comes before it.",
"through" : "in one side or end of something and out the other.",
"underneath" : "below or under",
"location" : "a particular place or position",
"fairness" : "impartial and just treatment or behavior without favoritism or discrimination",
"equity" : "the quality of being fair and impartial",
"protest" : "a statement or action expressing disapproval or objection to something."
}